{
  "display": {
    "icon": {
      "item": "minecraft:spectral_arrow"
    },
    "title": {
      "translate": "Пронзительный выстрел"
    },
    "description": {
      "translate": "Убейте пять мобов одним выстрелом арбалета"
    },
    "announce_to_chat": false,
    "frame": "challenge"
  },
  "parent": "blazeandcave:enchanting/shotbow",
  "rewards": {
    "function": "bc_rewards:enchanting/arbalistic"
  },
  "criteria": {
    "arbalistic": {
      "trigger": "minecraft:killed_by_crossbow",
      "conditions": {
        "victims": [],
        "unique_entity_types": 5
      }
    }
  }
}