{
  "display": {
    "icon": {
      "item": "minecraft:iron_axe"
    },
    "title": {
      "translate": "Грустное прощание"
    },
    "description": {
      "translate": "Убить аксолотля топором"
    },
    "announce_to_chat": "true"
  },
  "parent": "blazeandcave:animal/axolittle",
  "rewards": {
    "function": "bc_rewards:animal/axeolotl"
  },
  "criteria": {
    "axeolotl": {
      "trigger": "minecraft:player_killed_entity",
      "conditions": {
        "entity": {
          "type": "axolotl",
          "distance": {
            "absolute": {
              "max": 5
            }
          }
        },
        "player": {
          "equipment": {
            "mainhand": {
              "tag": "blazeandcave:axes"
            }
          }
        }
      }
    }
  }
}